flask_pyfcm.py
Flask_PyFCM-0.1.1.dist-info/DESCRIPTION.rst
Flask_PyFCM-0.1.1.dist-info/metadata.json
Flask_PyFCM-0.1.1.dist-info/RECORD
Flask_PyFCM-0.1.1.dist-info/METADATA
Flask_PyFCM-0.1.1.dist-info/top_level.txt
Flask_PyFCM-0.1.1.dist-info/WHEEL
